py_code_visualizer-1.0.1.dist-info/licenses/LICENSE
pyvisualizer/__init__.py
pyvisualizer/cli.py
pyvisualizer/core/__init__.py
pyvisualizer/core/analyzer.py
pyvisualizer/core/graph.py
pyvisualizer/core/resolver.py
pyvisualizer/templates/__init__.py
pyvisualizer/utils/__init__.py
pyvisualizer/utils/file_discovery.py
pyvisualizer/visualizers/__init__.py
pyvisualizer/visualizers/d3.py
pyvisualizer/visualizers/mermaid.py
py_code_visualizer-1.0.1.dist-info/METADATA
py_code_visualizer-1.0.1.dist-info/WHEEL
py_code_visualizer-1.0.1.dist-info/entry_points.txt
py_code_visualizer-1.0.1.dist-info/top_level.txt
py_code_visualizer-1.0.1.dist-info/RECORD
