Metadata-Version: 2.4
Name: py-code-visualizer
Version: 1.0.1
Summary: Transform complex Python codebases into beautiful interactive diagrams
Home-page: https://github.com/haider1998/PyVisualizer
Author: Syed Mohd Haider Rizvi
Author-email: Syed Mohd Haider Rizvi <smhrizvi281@gmail.com>
License: MIT
Project-URL: Homepage, https://github.com/haider1998/PyVisualizer
Project-URL: Documentation, https://github.com/haider1998/PyVisualizer#readme
Project-URL: Repository, https://github.com/haider1998/PyVisualizer
Project-URL: Issues, https://github.com/haider1998/PyVisualizer/issues
Keywords: visualization,code-analysis,architecture,diagram,mermaid,d3,python,ast,documentation
Classifier: Development Status :: 5 - Production/Stable
Classifier: Intended Audience :: Developers
Classifier: Topic :: Software Development :: Documentation
Classifier: Topic :: Software Development :: Quality Assurance
Classifier: Programming Language :: Python :: 3
Classifier: Programming Language :: Python :: 3.8
Classifier: Programming Language :: Python :: 3.9
Classifier: Programming Language :: Python :: 3.10
Classifier: Programming Language :: Python :: 3.11
Classifier: Programming Language :: Python :: 3.12
Classifier: License :: OSI Approved :: MIT License
Classifier: Operating System :: OS Independent
Requires-Python: >=3.8
License-File: LICENSE
Requires-Dist: networkx>=3.0
Provides-Extra: dev
Requires-Dist: pytest>=7.0.0; extra == "dev"
Requires-Dist: pytest-cov>=4.0.0; extra == "dev"
Requires-Dist: black>=23.0.0; extra == "dev"
Requires-Dist: mypy>=1.0.0; extra == "dev"
Requires-Dist: flake8>=6.0.0; extra == "dev"
Requires-Dist: isort>=5.12.0; extra == "dev"
Provides-Extra: graphviz
Requires-Dist: graphviz>=0.20.0; extra == "graphviz"
Provides-Extra: all
Requires-Dist: graphviz>=0.20.0; extra == "all"
Dynamic: author
Dynamic: home-page
Dynamic: license-file
Dynamic: requires-python
